[
  {
    "id": "par_h_001",
    "question": "y = 3x² − 12x + 7 parabolünün tepe noktası nedir?",
    "options": ["(2,-5)", "(2, -1)", "(2,1)", "(2,5)"],
    "correct": "(2,-5)"
  },
  {
    "id": "par_h_002",
    "question": "y = -2x² + 8x - 6 parabolünün maksimum değeri nedir?",
    "options": ["2", "10", "−2", "6"],
    "correct": "2"
  },
  {
    "id": "par_h_003",
    "question": "y = x² − 4x + 5 parabolünün simetri ekseni ve tepe noktası?",
    "options": ["x=2, (2,1)", "x=2, (2,-1)", "x=-2, (-2,1)", "x=-2, (-2,-1)"],
    "correct": "x=2, (2,1)"
  }
]
